MANIFEST.in
setup.py
tarea3/__init__.py
tarea3/principal.py
tarea3/controladores/__init__.py
tarea3/controladores/menu.py
tarea3/controladores/mostrar_reservas.py
tarea3/controladores/reservar.py
tarea3/modelos/__init__.py
tarea3/modelos/datos.py
tarea3/modelos/reservas.db
tarea3/modelos/reservas.sql
tarea3/recursos/misrecursos.qrc
tarea3/recursos/misrecursos_rc.py
tarea3/recursos/img/fondo_menu.jpg
tarea3/recursos/img/logo.jpg
tarea3/vistas/__init__.py
tarea3/vistas/menu.py
tarea3/vistas/menu.ui
tarea3/vistas/mostrar_reservas.py
tarea3/vistas/mostrar_reservas.ui
tarea3/vistas/reservar.py
tarea3/vistas/reservar.ui
tarea3_daaj.egg-info/PKG-INFO
tarea3_daaj.egg-info/SOURCES.txt
tarea3_daaj.egg-info/dependency_links.txt
tarea3_daaj.egg-info/top_level.txt