Metadata-Version: 2.4
Name: tarea3-daaj
Version: 1.2
Summary: Aplicación de gestión de reservas
Author: Diego Alexander Albarracín Jacho
Dynamic: author
Dynamic: summary
